<AllTestCases>
	<StepParametersFilePath>SubjectListParameters.xml</StepParametersFilePath>
    <StepAssembly>com.wanmei.mobile.iat.post.steps.</StepAssembly>
    <StepGroup>SubjectListSteps</StepGroup>
    <TestCase ID="Test01" Name="Test01NotLoginSubjectList">
	    <Step StepName="subjectList" StepParameterID="Test01"/>
       		
    </TestCase>
	<TestCase ID="Test02" Name="Test02AddSubscription">
	    <Step StepName="login" StepAssembly="com.wanmei.mobile.iat.sdk.steps." StepGroup="LoginSteps" StepParameterID="Test02"/>
	    <Step StepName="subjectList" StepParameterID="Test02"/>
       		
    </TestCase>
	<TestCase ID="Test03" Name="Test03DelSubscription">
	    <Step StepName="login" StepAssembly="com.wanmei.mobile.iat.sdk.steps." StepGroup="LoginSteps" StepParameterID="Test03"/>
	    <Step StepName="subjectList" StepParameterID="Test03"/>
       		
    </TestCase>
    
</AllTestCases>